Space_Weather_Interface_P/__init__.py
Space_Weather_Interface_P/main.py
Space_Weather_Interface_P/makem.py
Space_Weather_Interface_P/sdo_image_getter.py
Space_Weather_Interface_P/sdo_movie.py
Space_Weather_Interface_P/soho_image_getter.py
Space_Weather_Interface_P/soho_movie.py
Space_Weather_Interface_P-1.0.12.dist-info/LICENSE.txt
Space_Weather_Interface_P-1.0.12.dist-info/METADATA
Space_Weather_Interface_P-1.0.12.dist-info/WHEEL
Space_Weather_Interface_P-1.0.12.dist-info/entry_points.txt
Space_Weather_Interface_P-1.0.12.dist-info/top_level.txt
Space_Weather_Interface_P-1.0.12.dist-info/RECORD
